CHANGES.md
MANIFEST.in
README.md
setup.cfg
setup.py
test-requirements.txt
wukong/__init__.py
wukong/api.py
wukong/errors.py
wukong/models.py
wukong/query.py
wukong/request.py
wukong/zookeeper.py
wukong.egg-info/PKG-INFO
wukong.egg-info/SOURCES.txt
wukong.egg-info/dependency_links.txt
wukong.egg-info/requires.txt
wukong.egg-info/top_level.txt