Metadata-Version: 1.1
Name: wukong
Version: 0.5.0
Summary: An ORM Client library for SolrCloud
Home-page: https://github.com/SurveyMonkey/wukong
Author: Da Kuang
Author-email: dkuang1980@gmail.com
License: UNKNOWN
Keywords: solr cloud solrcloud client python orm
Platform: UNKNOWN
Classifier: Topic :: Software Development :: Libraries :: Python Modules
Classifier: License :: OSI Approved :: MIT License
Classifier: Natural Language :: English
Classifier: Operating System :: OS Independent
Classifier: Programming Language :: Python
